cryptocurrencychart/__init__.py
cryptocurrencychart/api.py
cryptocurrencychart/config.py
cryptocurrencychart/urls.py
cryptocurrencychart/version.py
tests/__init__.py
tests/test_cryptocurrencychart.py
cryptocurrencychart-1.0.0.dist-info/LICENSE
cryptocurrencychart-1.0.0.dist-info/METADATA
cryptocurrencychart-1.0.0.dist-info/WHEEL
cryptocurrencychart-1.0.0.dist-info/top_level.txt
cryptocurrencychart-1.0.0.dist-info/RECORD
