Metadata-Version: 2.1
Name: cryptocurrencychart
Version: 1.0.0
Summary: cryptocurrencychart is a wrapper around the cryptocurrencychart.com api.
Home-page: https://github.com/gdoermann/cryptocurrencychart
Author: Greg Doermann
Author-email: greg@that.bz
License: UNKNOWN
Platform: UNKNOWN
Requires-Dist: requests
